formulary/__init__.py
formulary/cli.py
formulary/cloudformation.py
formulary/config.py
formulary/controller.py
formulary/records.py
formulary/s3.py
formulary/template.py
formulary/utils.py
formulary/builders/__init__.py
formulary/builders/base.py
formulary/builders/ec2.py
formulary/builders/elasticache.py
formulary/builders/elb.py
formulary/builders/environment.py
formulary/builders/rds.py
formulary/builders/route53.py
formulary/builders/service.py
formulary/builders/stack.py
formulary/resources/__init__.py
formulary/resources/autoscaling.py
formulary/resources/base.py
formulary/resources/cloudformation.py
formulary/resources/ec2.py
formulary/resources/elasticache.py
formulary/resources/elb.py
formulary/resources/rds.py
formulary/resources/route53.py
formulary-0.3.6.dist-info/zip-safe
formulary-0.3.6.dist-info/top_level.txt
formulary-0.3.6.dist-info/entry_points.txt
formulary-0.3.6.dist-info/METADATA
formulary-0.3.6.dist-info/DESCRIPTION.rst
formulary-0.3.6.dist-info/metadata.json
formulary-0.3.6.dist-info/WHEEL
formulary-0.3.6.dist-info/RECORD
